simpleperceptron/ActivationFuncs.py
simpleperceptron/BackwardPropagator.py
simpleperceptron/ForwardPropagator.py
simpleperceptron/Perceptron.py
simpleperceptron/__init__.py
simpleperceptron-0.1.1.dist-info/LICENSE
simpleperceptron-0.1.1.dist-info/METADATA
simpleperceptron-0.1.1.dist-info/WHEEL
simpleperceptron-0.1.1.dist-info/top_level.txt
simpleperceptron-0.1.1.dist-info/RECORD
